.DS_Store
MANIFEST.in
readme.md
requirements.txt
setup.py
test.py
cocoNLP/__init__.py
cocoNLP/__version__.py
cocoNLP/extractor.py
cocoNLP.egg-info/PKG-INFO
cocoNLP.egg-info/SOURCES.txt
cocoNLP.egg-info/dependency_links.txt
cocoNLP.egg-info/requires.txt
cocoNLP.egg-info/top_level.txt
cocoNLP/config/basic/time_nlp/.DS_Store
cocoNLP/config/basic/time_nlp/LunarSolarConverter.py
cocoNLP/config/basic/time_nlp/README.md
cocoNLP/config/basic/time_nlp/RangeTimeEnum.py
cocoNLP/config/basic/time_nlp/StringPreHandler.py
cocoNLP/config/basic/time_nlp/Test.py
cocoNLP/config/basic/time_nlp/TimeNormalizer.py
cocoNLP/config/basic/time_nlp/TimePoint.py
cocoNLP/config/basic/time_nlp/TimeUnit.py
cocoNLP/config/basic/time_nlp/__init__.py
cocoNLP/config/basic/time_nlp/EGG-INFO/PKG-INFO
cocoNLP/config/basic/time_nlp/EGG-INFO/SOURCES.txt
cocoNLP/config/basic/time_nlp/EGG-INFO/dependency_links.txt
cocoNLP/config/basic/time_nlp/EGG-INFO/not-zip-safe
cocoNLP/config/basic/time_nlp/EGG-INFO/requires.txt
cocoNLP/config/basic/time_nlp/EGG-INFO/top_level.txt
cocoNLP/config/basic/time_nlp/TimeConverter.egg-info/PKG-INFO
cocoNLP/config/basic/time_nlp/TimeConverter.egg-info/SOURCES.txt
cocoNLP/config/basic/time_nlp/TimeConverter.egg-info/dependency_links.txt
cocoNLP/config/basic/time_nlp/TimeConverter.egg-info/not-zip-safe
cocoNLP/config/basic/time_nlp/TimeConverter.egg-info/requires.txt
cocoNLP/config/basic/time_nlp/TimeConverter.egg-info/top_level.txt
cocoNLP/config/basic/time_nlp/__pycache__/LunarSolarConverter.cpython-35.pyc
cocoNLP/config/basic/time_nlp/__pycache__/LunarSolarConverter.cpython-36.pyc
cocoNLP/config/basic/time_nlp/__pycache__/RangeTimeEnum.cpython-35.pyc
cocoNLP/config/basic/time_nlp/__pycache__/RangeTimeEnum.cpython-36.pyc
cocoNLP/config/basic/time_nlp/__pycache__/StringPreHandler.cpython-35.pyc
cocoNLP/config/basic/time_nlp/__pycache__/StringPreHandler.cpython-36.pyc
cocoNLP/config/basic/time_nlp/__pycache__/Test.cpython-36.pyc
cocoNLP/config/basic/time_nlp/__pycache__/TimeNormalizer.cpython-35.pyc
cocoNLP/config/basic/time_nlp/__pycache__/TimeNormalizer.cpython-36.pyc
cocoNLP/config/basic/time_nlp/__pycache__/TimePoint.cpython-35.pyc
cocoNLP/config/basic/time_nlp/__pycache__/TimePoint.cpython-36.pyc
cocoNLP/config/basic/time_nlp/__pycache__/TimeUnit.cpython-35.pyc
cocoNLP/config/basic/time_nlp/__pycache__/TimeUnit.cpython-36.pyc
cocoNLP/config/basic/time_nlp/__pycache__/__init__.cpython-35.pyc
cocoNLP/config/basic/time_nlp/__pycache__/__init__.cpython-36.pyc
cocoNLP/config/basic/time_nlp/resource/__init__.py
cocoNLP/config/basic/time_nlp/resource/holi_lunar.json
cocoNLP/config/basic/time_nlp/resource/holi_solar.json
cocoNLP/config/basic/time_nlp/resource/reg.pkl
cocoNLP/config/basic/time_nlp/resource/regex.txt
cocoNLP/config/basic/time_nlp/resource/__pycache__/__init__.cpython-36.pyc
cocoNLP/config/phrase/rake.py
